{
    "Old_Dominion\\Chain_Bridge_Partners\\2021.07.02 - Chain Bridge Partners - Deed of Lease.pdf": {
        "file_name": "Chain Bridge Partners - Deed of Lease",
        "building_name": "Old Dominion",
        "tenant_name": "Chain Bridge Partners",
        "date": "2021.07.02"
    },
    "Old_Dominion\\Chain_Bridge_Partners\\Chain Bridge Partners - Commencement.pdf": {
        "file_name": "Chain Bridge Partners - Commencement.pdf",
        "building_name": "Old Dominion",
        "tenant_name": "Chain Bridge Partners",
        "date": ""
    },
    "Old_Dominion\\Collis_&_Associates\\2015.01.07 - Collis & Associates - Original Lease dtd.pdf": {
        "file_name": "Collis & Associates - Original Lease dtd",
        "building_name": "Old Dominion",
        "tenant_name": "Collis & Associates",
        "date": "2015.01.07"
    },
    "Old_Dominion\\Collis_&_Associates\\2015.03.30 - Collis & Associates - Exhibit B dtd.pdf": {
        "file_name": "Collis & Associates - Exhibit B dtd",
        "building_name": "Old Dominion",
        "tenant_name": "Collis & Associates",
        "date": "2015.03.30"
    },
    "Old_Dominion\\Collis_&_Associates\\2017.04.03 - Collis & Associates - 1st Amendment dtd.pdf": {
        "file_name": "Collis & Associates - 1st Amendment dtd",
        "building_name": "Old Dominion",
        "tenant_name": "Collis & Associates",
        "date": "2017.04.03"
    },
    "Old_Dominion\\Collis_&_Associates\\2019.09.05 - Collis & Associates - 2nd Amendment.pdf": {
        "file_name": "Collis & Associates - 2nd Amendment",
        "building_name": "Old Dominion",
        "tenant_name": "Collis & Associates",
        "date": "2019.09.05"
    },
    "Old_Dominion\\Collis_&_Associates\\Collis & Associates - Commencement_2nd Amendment.pdf": {
        "file_name": "Collis & Associates - Commencement_2nd Amendment.pdf",
        "building_name": "Old Dominion",
        "tenant_name": "Collis & Associates",
        "date": ""
    },
    "Old_Dominion\\Dell_Management\\Dell Management - Storage License Agreement.pdf": {
        "file_name": "Dell Management - Storage License Agreement.pdf",
        "building_name": "Old Dominion",
        "tenant_name": "Dell Management",
        "date": ""
    },
    "Old_Dominion\\Dell_Management\\Dell Management - Third Ammendment to the Lease.pdf": {
        "file_name": "Dell Management - Third Ammendment to the Lease.pdf",
        "building_name": "Old Dominion",
        "tenant_name": "Dell Management",
        "date": ""
    },
    "Old_Dominion\\General_Counsel\\2014.01.28 - General Counsel - Original lease dtd.pdf": {
        "file_name": "General Counsel - Original lease dtd",
        "building_name": "Old Dominion",
        "tenant_name": "General Counsel",
        "date": "2014.01.28"
    },
    "Old_Dominion\\General_Counsel\\2014.03.13 - General Counsel - Exhibit B dtd.pdf": {
        "file_name": "General Counsel - Exhibit B dtd",
        "building_name": "Old Dominion",
        "tenant_name": "General Counsel",
        "date": "2014.03.13"
    },
    "Old_Dominion\\General_Counsel\\2016.02.16 - General Counsel - 1st Amendment dtd.pdf": {
        "file_name": "General Counsel - 1st Amendment dtd",
        "building_name": "Old Dominion",
        "tenant_name": "General Counsel",
        "date": "2016.02.16"
    },
    "Old_Dominion\\General_Counsel\\2018.01.24 - General Counsel - 2nd Amendment.pdf": {
        "file_name": "General Counsel - 2nd Amendment",
        "building_name": "Old Dominion",
        "tenant_name": "General Counsel",
        "date": "2018.01.24"
    },
    "Old_Dominion\\General_Counsel\\2019.02.01 - General Counsel - 3rd Amendment.pdf": {
        "file_name": "General Counsel - 3rd Amendment",
        "building_name": "Old Dominion",
        "tenant_name": "General Counsel",
        "date": "2019.02.01"
    },
    "Old_Dominion\\General_Counsel\\General Counsel - Monument Signage Agreement.pdf": {
        "file_name": "General Counsel - Monument Signage Agreement.pdf",
        "building_name": "Old Dominion",
        "tenant_name": "General Counsel",
        "date": ""
    },
    "Old_Dominion\\J-N_Vision\\1998.09.10 - Dr. Wendy Garson, Dr. Robert Jacobs and Dr. Duc Nguyen - Deed of Lease dtd.pdf": {
        "file_name": "Dr. Wendy Garson, Dr. Robert Jacobs and Dr. Duc Nguyen - Deed of Lease dtd",
        "building_name": "Old Dominion",
        "tenant_name": "J-N Vision",
        "date": "1998.09.10"
    },
    "Old_Dominion\\J-N_Vision\\2001.06.26 - Dr. Wendy Garson, Dr. Robert Jacobs and Dr. Duc Nguyen - 1st Amendment dtd.pdf": {
        "file_name": "Dr. Wendy Garson, Dr. Robert Jacobs and Dr. Duc Nguyen - 1st Amendment dtd",
        "building_name": "Old Dominion",
        "tenant_name": "J-N Vision",
        "date": "2001.06.26"
    },
    "Old_Dominion\\J-N_Vision\\2004.06.30 - Dr. Wendy Garson, Dr. Robert Jacobs and Dr. Duc Nguyen - 2nd Amendment dtd.pdf": {
        "file_name": "Dr. Wendy Garson, Dr. Robert Jacobs and Dr. Duc Nguyen - 2nd Amendment dtd",
        "building_name": "Old Dominion",
        "tenant_name": "J-N Vision",
        "date": "2004.06.30"
    },
    "Old_Dominion\\J-N_Vision\\2007.10.15 - Dr. Wendy Garson, Dr. Robert Jacobs and Dr. Duc Nguyen - 3rd Amendment dtd.pdf": {
        "file_name": "Dr. Wendy Garson, Dr. Robert Jacobs and Dr. Duc Nguyen - 3rd Amendment dtd",
        "building_name": "Old Dominion",
        "tenant_name": "J-N Vision",
        "date": "2007.10.15"
    },
    "Old_Dominion\\J-N_Vision\\2010.10.26 - Dr. Wendy Garson, Dr. Robert Jacobs and Dr. Duc Nguyen - 4th Amendment dtd.pdf": {
        "file_name": "Dr. Wendy Garson, Dr. Robert Jacobs and Dr. Duc Nguyen - 4th Amendment dtd",
        "building_name": "Old Dominion",
        "tenant_name": "J-N Vision",
        "date": "2010.10.26"
    },
    "Old_Dominion\\J-N_Vision\\2013.10.01 - Dr. Wendy Garson, Dr. Robert Jacobs and Dr. Duc Nguyen - 5th Amendment dtd.pdf": {
        "file_name": "Dr. Wendy Garson, Dr. Robert Jacobs and Dr. Duc Nguyen - 5th Amendment dtd",
        "building_name": "Old Dominion",
        "tenant_name": "J-N Vision",
        "date": "2013.10.01"
    },
    "Old_Dominion\\J-N_Vision\\2014.06.03 - Dr. Wendy Garson, Dr. Robert Jacobs and Dr. Duc Nguyen  - Exhibit C-2 dtd.pdf": {
        "file_name": "Dr. Wendy Garson, Dr. Robert Jacobs and Dr. Duc Nguyen  - Exhibit C-2 dtd",
        "building_name": "Old Dominion",
        "tenant_name": "J-N Vision",
        "date": "2014.06.03"
    },
    "Old_Dominion\\J-N_Vision\\2021.10.05 - J-N Vision - 6th Amendment.pdf": {
        "file_name": "J-N Vision - 6th Amendment",
        "building_name": "Old Dominion",
        "tenant_name": "J-N Vision",
        "date": "2021.10.05"
    },
    "Old_Dominion\\J-N_Vision\\2024.04.22 - J-N Vision -  7th Amendment Executed.pdf": {
        "file_name": "J-N Vision -  7th Amendment Executed",
        "building_name": "Old Dominion",
        "tenant_name": "J-N Vision",
        "date": "2024.04.22"
    },
    "Old_Dominion\\J-N_Vision\\J-N Vision - Commencement Cert.pdf": {
        "file_name": "J-N Vision - Commencement Cert.pdf",
        "building_name": "Old Dominion",
        "tenant_name": "J-N Vision",
        "date": ""
    },
    "Old_Dominion\\Johns_Hopkins_Community_Physicians\\JHCP - Commencement Executed.pdf": {
        "file_name": "JHCP - Commencement Executed.pdf",
        "building_name": "Old Dominion",
        "tenant_name": "Johns Hopkins Community Physicians",
        "date": ""
    },
    "Old_Dominion\\Johns_Hopkins_Community_Physicians\\JHCP - Signage Approval Letter.pdf": {
        "file_name": "JHCP - Signage Approval Letter.pdf",
        "building_name": "Old Dominion",
        "tenant_name": "Johns Hopkins Community Physicians",
        "date": ""
    }
}